silasdk/__init__.py
silasdk/businessInformation.py
silasdk/businessOperations.py
silasdk/client.py
silasdk/documents.py
silasdk/endpoints.py
silasdk/errors.py
silasdk/ethwallet.py
silasdk/message.py
silasdk/processingTypes.py
silasdk/registrationFields.py
silasdk/schema.py
silasdk/transactions.py
silasdk/users.py
silasdk/wallet.py
silasdk/utils/__init__.py
silasdk/utils/url_parameters.py
silasdk-0.2.53.dist-info/LICENSE.txt
silasdk-0.2.53.dist-info/METADATA
silasdk-0.2.53.dist-info/WHEEL
silasdk-0.2.53.dist-info/top_level.txt
silasdk-0.2.53.dist-info/RECORD
