Metadata-Version: 2.1
Name: silasdk
Version: 0.2.53
Summary: Sila Python library for message signing and api wrapper
Home-page: https://github.com/Sila-Money/Sila-Python
Author: Sila
Author-email: support@silamoney.com
License: Apache
Keywords: Sila v0.2.53 Rest API
Classifier: Development Status :: 4 - Beta
Classifier: Intended Audience :: Developers
Classifier: License :: OSI Approved :: MIT License
Classifier: Programming Language :: Python :: 3.7
Classifier: Programming Language :: Python :: 3.8
Classifier: Programming Language :: Python :: 3.9
License-File: LICENSE.txt
Requires-Dist: requests (==2.31.0)
Requires-Dist: pyaml (>=15.8.2)
Requires-Dist: eth-account (==0.8.0)
Requires-Dist: web3 (==6.5.0)
